data memory/data_memory.v


module data_memory (
     
    l, 
    address, 
    clk, 
    q,
    write_data
);

reg [63:0][0:31]r;
input l, clk;
input [63:0]address;
input [63:0] write_data;
output [63:0][0:0]q;

assign #2 q = r[address];

always @(posedge clk) begin
    if(l) begin
        r[address] <= #3 write_data;
    end
    
end

endmodule

part1/data memory/data_memory_tb.v
`timescale 1ns/1ns
`include "data_memory.v"

module data_memory_tb;

reg clk;
reg l;
reg [63:0]write_data;
reg [63:0]address;
wire [63:0][0:0]q;
integer i;

data_memory UUT(
    .l(l),
    .address(address),
    .clk(clk),
    .q(q),
    .write_data(write_data)
);

always #5 clk = ~clk;

initial begin
    $dumpfile("data_memory_tb.vcd");
    $dumpvars(0, data_memory_tb);
end

initial begin
    
    clk=1;

    l=1;  // if l == 1 then it writes the data in data memory
    write_data = 64'd1;
    address = 64'd0;
    #10;
    if(q != 64'd1)
        $display("Error occured in first test");
/////////////////

    l=0;
    write_data = 64'd2;
    address = 64'd0;
    //in this test, content of data memory is as same as before.
    #10;
    if(q != 64'd1)
        $display("Error occured in second test");


    l=1;
    write_data = 64'd100;
    address = 64'd12;
    #10;
    if(q != 64'd100)
        $display("Error occured in third test");

    
    l=0;
    write_data = 64'd125;
    address = 64'd111;
    #10;
    if(q != 64'd0)
        $display("Error occured in forth test");

    l=1;
    write_data = 64'd150;
    address = 64'd300;
    #10;
    if(q != 64'd150)
        $display("Error occured in fifth test");

    
    l=1;
    write_data = 64'd322;
    address = 64'd300;
    #10;
    if(q != 64'd322)
        $display("Error occured in sixth test");


    l=0;
    write_data = 64'd322;
    address = 64'd0;
    #10;
    if(q != 64'd1)
        $display("Error occured in sixth test");
    $finish;
end

endmodule

data memory/data_memory_tb.vcd
$date
	Fri Dec 10 13:43:47 2021
$end
$version
	Icarus Verilog
$end
$timescale
	1ns
$end
$scope module data_memory_tb $end
$var wire 64 ! q [63:0] $end
$var reg 64 " address [63:0] $end
$var reg 1 # clk $end
$var reg 1 $ l $end
$var reg 64 % write_data [63:0] $end
$scope module UUT $end
$var wire 64 & address [63:0] $end
$var wire 1 # clk $end
$var wire 1 $ l $end
$var wire 64 ' write_data [63:0] $end
$var wire 64 ( q [63:0] $end
$var reg 2048 ) r [2047:0] $end
$upscope $end
$upscope $end
$enddefinitions $end
#0
$dumpvars
bx )
bx (
b1 '
b0 &
b1 %
1$
1#
b0 "
bx !
$end
#2
b0xxxxxxxxxxxxxxxxxxxxxxxxxxxxxxxx !
b0xxxxxxxxxxxxxxxxxxxxxxxxxxxxxxxx (
#3
bx00000000000000000000000000000001 )
#5
b1 !
b1 (
0#
#10
1#
b10 %
b10 '
0$
#15
0#
#20
1#
b1100 "
b1100 &
b1100100 %
b1100100 '
1$
#22
b0xxxxxxxxxxxxxxxxxxxxxxxxxxxxxxxx !
b0xxxxxxxxxxxxxxxxxxxxxxxxxxxxxxxx (
#23
bx00000000000000000000000001100100xxxxxxxxxxxxxxxxxxxxxxxxxxxxxxxxxxxxxxxxxxxxxxxxxxxxxxxxxxxxxxxxxxxxxxxxxxxxxxxxxxxxxxxxxxxxxxxxxxxxxxxxxxxxxxxxxxxxxxxxxxxxxxxxxxxxxxxxxxxxxxxxxxxxxxxxxxxxxxxxxxxxxxxxxxxxxxxxxxxxxxxxxxxxxxxxxxxxxxxxxxxxxxxxxxxxxxxxxxxxxxxxxxxxxxxxxxxxxxxxxxxxxxxxxxxxxxxxxxxxxxxxxxxxxxxxxxxxxxxxxxxxxxxxxxxxxxxxxxxxxxxxxxxxxxxxxxxxxxxxxxxxxxxxxxxxxxxxxxxxxxxxxxxxxxxx00000000000000000000000000000001 )
#25
b1100100 !
b1100100 (
0#
#30
1#
b1101111 "
b1101111 &
b1111101 %
b1111101 '
0$
#32
b0xxxxxxxxxxxxxxxxxxxxxxxxxxxxxxxx !
b0xxxxxxxxxxxxxxxxxxxxxxxxxxxxxxxx (
#35
0#
#40
1#
b100101100 "
b100101100 &
b10010110 %
b10010110 '
1$
#45
0#
#50
1#
b101000010 %
b101000010 '
#55
0#
#60
1#
b0 "
b0 &
0$
#62
b1 !
b1 (
