part2/mux2_64bit/mux2_64bit.v
module mux2to1 (
    w, s, f
);
input [1:0]w;
input s;
output reg f;

always @(*) begin
    if(s==0)
        f=w[0];
    else
        f=w[1];
end
    
endmodule



module mux2_64bit (
     w, s, f
);
input [127:0]w;
input s;
output [0:63]f;

    mux2to1 mux1({w[127], w[63]}, s, f[0]);
    mux2to1 mux2({w[126], w[62]}, s, f[1]);
    mux2to1 mux3({w[125], w[61]}, s, f[2]);
    mux2to1 mux4({w[124], w[60]}, s, f[3]);
    mux2to1 mux5({w[123], w[59]}, s, f[4]);
    mux2to1 mux6({w[122], w[58]}, s, f[5]);
    mux2to1 mux7({w[121], w[57]}, s, f[6]);
    mux2to1 mux8({w[120], w[56]}, s, f[7]);
    mux2to1 mux9({w[119], w[55]}, s, f[8]);
    mux2to1 mux10({w[118], w[54]}, s, f[9]);
    mux2to1 mux11({w[117], w[53]}, s, f[10]);
    mux2to1 mux12({w[116], w[52]}, s, f[11]);
    mux2to1 mux13({w[115], w[51]}, s, f[12]);
    mux2to1 mux14({w[114], w[50]}, s, f[13]);
    mux2to1 mux15({w[113], w[49]}, s, f[14]);
    mux2to1 mux16({w[112], w[48]}, s, f[15]);
    mux2to1 mux17({w[111], w[47]}, s, f[16]);
    mux2to1 mux18({w[110], w[46]}, s, f[17]);
    mux2to1 mux19({w[109], w[45]}, s, f[18]);
    mux2to1 mux20({w[108], w[44]}, s, f[19]);
    mux2to1 mux21({w[107], w[43]}, s, f[20]);
    mux2to1 mux22({w[106], w[42]}, s, f[21]);
    mux2to1 mux23({w[105], w[41]}, s, f[22]);
    mux2to1 mux24({w[104], w[40]}, s, f[23]);
    mux2to1 mux25({w[103], w[39]}, s, f[24]);
    mux2to1 mux26({w[102], w[38]}, s, f[25]);
    mux2to1 mux27({w[101], w[37]}, s, f[26]);
    mux2to1 mux28({w[100], w[36]}, s, f[27]);
    mux2to1 mux29({w[99], w[35]}, s, f[28]);
    mux2to1 mux30({w[98], w[34]}, s, f[29]);
    mux2to1 mux31({w[97], w[33]}, s, f[30]);
    mux2to1 mux32({w[96], w[32]}, s, f[31]);
    mux2to1 mux33({w[95], w[31]}, s, f[32]);
    mux2to1 mux34({w[94], w[30]}, s, f[33]);
    mux2to1 mux35({w[93], w[29]}, s, f[34]);
    mux2to1 mux36({w[92], w[28]}, s, f[35]);
    mux2to1 mux37({w[91], w[27]}, s, f[36]);
    mux2to1 mux38({w[90], w[26]}, s, f[37]);
    mux2to1 mux39({w[89], w[25]}, s, f[38]);
    mux2to1 mux40({w[88], w[24]}, s, f[39]);
    mux2to1 mux41({w[87], w[23]}, s, f[40]);
    mux2to1 mux42({w[86], w[22]}, s, f[41]);
    mux2to1 mux43({w[85], w[21]}, s, f[42]);
    mux2to1 mux44({w[84], w[20]}, s, f[43]);
    mux2to1 mux45({w[83], w[19]}, s, f[44]);
    mux2to1 mux46({w[82], w[18]}, s, f[45]);
    mux2to1 mux47({w[81], w[17]}, s, f[46]);
    mux2to1 mux48({w[80], w[16]}, s, f[47]);
    mux2to1 mux49({w[79], w[15]}, s, f[48]);
    mux2to1 mux50({w[78], w[14]}, s, f[49]);
    mux2to1 mux51({w[77], w[13]}, s, f[50]);
    mux2to1 mux52({w[76], w[12]}, s, f[51]);
    mux2to1 mux53({w[75], w[11]}, s, f[52]);
    mux2to1 mux54({w[74], w[10]}, s, f[53]);
    mux2to1 mux55({w[73], w[9]}, s, f[54]);
    mux2to1 mux56({w[72], w[8]}, s, f[55]);
    mux2to1 mux57({w[71], w[7]}, s, f[56]);
    mux2to1 mux58({w[70], w[6]}, s, f[57]);
    mux2to1 mux59({w[69], w[5]}, s, f[58]);
    mux2to1 mux60({w[68], w[4]}, s, f[59]);
    mux2to1 mux61({w[67], w[3]}, s, f[60]);
    mux2to1 mux62({w[66], w[2]}, s, f[61]);
    mux2to1 mux63({w[65], w[1]}, s, f[62]);
    mux2to1 mux64({w[64], w[0]}, s, f[63]);
    

endmodule

part2/mux2_64bit/mux2_64bit_tb.v
`timescale 1ns/1ns
`include "mux2_64bit.v"

module mux2_64bit_tb;

reg [127:0]w;
reg s;
wire [0:63]f;
integer i;

mux2_64bit UUT (.w(w), .s(s), .f(f));

initial begin
    $dumpfile("mux2_64bit_tb.vcd");
    $dumpvars(0, mux2_64bit_tb);

    for ( i=0 ; i<128; i++) begin
        w[i] = 0;
    end
    s=0;
    #10;
    for (i = 0 ; i<64; i++) begin
        if(f[i] != 0)
            $display("test failed");;
    end
      
    s=1;
    #10;

      
    for (i = 0 ; i<64; i++) begin
        if(f[i] != 0)
            $display("test failed");;
    end
w[0] = 1;
    for ( i=1 ; i<128; i++) begin
        w[i] = 0;
    end
    s=0;
    #10;

      
    
    
    if(f[63] != 1)
        $display("test failed1");
    for (i = 62 ; i>=0; i--) begin
        if(f[i] != 0)
            $display("test failed1.1");
    end
    s=1;
    #10;
      
    if(f[0] != 0)
        $display("test failed2");
    for (i = 1 ; i<64; i++) begin
        if(f[i] != 0)
            $display("test failed2.2");
    end
    w[0] = 0;
    w[1] = 1;
    for ( i=2 ; i<128; i++) begin
        w[i] = 0;
    end
    s=0;
    #10;


    
    if(f[63] != 0)
        $display("test failed");
    for (i = 62 ; i>=0; i--) begin
        if(f[i] != 0)
            $display("test failed");
    end
    s=1;
    #10;
    
    if(f[63] != 1)
        $display("test failed");
    for (i = 62 ; i>=0; i--) begin
        if(f[i] != 0)
            $display("test failed");
    end
    w[0] = 1;
    w[1] = 1;
    for ( i=2 ; i<128; i++) begin
        w[i] = 0;
    end
    s=0;
    #10;


    
    if(f[63] != 1)
        $display("test failed");
    for (i = 62 ; i>=0; i--) begin
        if(f[i] != 0)
            $display("test failed");
    end
    s=1;
    #10;
    
    if(f[63] != 1)
        $display("test failed");
    for (i = 62 ; i>=0; i--) begin
        if(f[i] != 0)
            $display("test failed");
    end
    w[0] = 0;
    w[1] = 0;
    w[2] = 1;
    for ( i=3 ; i<128; i++) begin
        w[i] = 0;
    end
    s=0;
    #10;


    
    if(f[63] != 0)
        $display("test failed");
    if(f[62] != 1)
        $display("test failed");
    for (i = 61 ; i>=0; i--) begin
        if(f[i] != 0)
            $display("test failed");
    end
    s=1;
    #10;
    
    if(f[63] != 0)
        $display("test failed");
    if(f[62] != 0)
        $display("test failed");
    for (i = 61 ; i>=0; i--) begin
        if(f[i] != 0)
            $display("test failed");
    end
    w[0] = 0;
    w[1] = 1;
    w[2] = 1;
    for ( i=3 ; i<128; i++) begin
        w[i] = 0;
    end
    s=0;
    #10;


    
    if(f[63] != 0)
        $display("test failed");
    if(f[62] != 1)
        $display("test failed");
    for (i = 61 ; i>=0; i--) begin
        if(f[i] != 0)
            $display("test failed");
    end
    s=1;
    #10;
    
    if(f[63] != 1)
        $display("test failed");
    if(f[62] != 0)
        $display("test failed");
    for (i = 61 ; i>=0; i--) begin
        if(f[i] != 0)
            $display("test failed");
    end
    w[0] = 1;
    w[1] = 0;
    w[2] = 1;
    for ( i=3 ; i<128; i++) begin
        w[i] = 0;
    end
    s=0;
    #10;


    
    if(f[63] != 1)
        $display("test failed");
    if(f[62] != 1)
        $display("test failed");
    for (i = 61 ; i>=0; i--) begin
        if(f[i] != 0)
            $display("test failed");
    end
    s=1;
    #10;
    
    if(f[63] != 0)
        $display("test failed");
    if(f[62] != 0)
        $display("test failed");
    for (i = 61 ; i>=0; i--) begin
        if(f[i] != 0)
            $display("test failed");
    end
    w[0] = 1;
    w[1] = 1;
    w[2] = 1;
    for ( i=3 ; i<128; i++) begin
        w[i] = 0;
    end
    s=0;
    #10;


    
    if(f[63] != 1)
        $display("test failed");
    if(f[62] != 1)
        $display("test failed");
    for (i = 61 ; i>=0; i--) begin
        if(f[i] != 0)
            $display("test failed");
    end
    s=1;
    #10;
    
    if(f[63] != 1)
        $display("test failed");
    if(f[62] != 0)
        $display("test failed");
    for (i = 61 ; i>=0; i--) begin
        if(f[i] != 0)
            $display("test failed");
    end
    #10;

    $display("test completed");
end

endmodule

part1/mux2_64bit/mux2_64bit_tb.vcd
$date
	Mon Nov 15 19:06:26 2021
$end
$version
	Icarus Verilog
$end
$timescale
	1ns
$end
$scope module mux2_64bit_tb $end
$var wire 64 ! f [0:63] $end
$var reg 1 " s $end
$var reg 128 # w [127:0] $end
$var integer 32 $ i [31:0] $end
$scope module UUT $end
$var wire 1 " s $end
$var wire 128 % w [127:0] $end
$var wire 64 & f [0:63] $end
$scope module mux1 $end
$var wire 1 " s $end
$var wire 2 ' w [1:0] $end
$var reg 1 ( f $end
$upscope $end
$scope module mux10 $end
$var wire 1 " s $end
$var wire 2 ) w [1:0] $end
$var reg 1 * f $end
$upscope $end
$scope module mux11 $end
$var wire 1 " s $end
$var wire 2 + w [1:0] $end
$var reg 1 , f $end
$upscope $end
$scope module mux12 $end
$var wire 1 " s $end
$var wire 2 - w [1:0] $end
$var reg 1 . f $end
$upscope $end
$scope module mux13 $end
$var wire 1 " s $end
$var wire 2 / w [1:0] $end
$var reg 1 0 f $end
$upscope $end
$scope module mux14 $end
$var wire 1 " s $end
$var wire 2 1 w [1:0] $end
$var reg 1 2 f $end
$upscope $end
$scope module mux15 $end
$var wire 1 " s $end
$var wire 2 3 w [1:0] $end
$var reg 1 4 f $end
$upscope $end
$scope module mux16 $end
$var wire 1 " s $end
$var wire 2 5 w [1:0] $end
$var reg 1 6 f $end
$upscope $end
$scope module mux17 $end
$var wire 1 " s $end
$var wire 2 7 w [1:0] $end
$var reg 1 8 f $end
$upscope $end
$scope module mux18 $end
$var wire 1 " s $end
$var wire 2 9 w [1:0] $end
$var reg 1 : f $end
$upscope $end
$scope module mux19 $end
$var wire 1 " s $end
$var wire 2 ; w [1:0] $end
$var reg 1 < f $end
$upscope $end
$scope module mux2 $end
$var wire 1 " s $end
$var wire 2 = w [1:0] $end
$var reg 1 > f $end
$upscope $end
$scope module mux20 $end
$var wire 1 " s $end
$var wire 2 ? w [1:0] $end
$var reg 1 @ f $end
$upscope $end
$scope module mux21 $end
$var wire 1 " s $end
$var wire 2 A w [1:0] $end
$var reg 1 B f $end
$upscope $end
$scope module mux22 $end
$var wire 1 " s $end
$var wire 2 C w [1:0] $end
$var reg 1 D f $end
$upscope $end
$scope module mux23 $end
$var wire 1 " s $end
$var wire 2 E w [1:0] $end
$var reg 1 F f $end
$upscope $end
$scope module mux24 $end
$var wire 1 " s $end
$var wire 2 G w [1:0] $end
$var reg 1 H f $end
$upscope $end
$scope module mux25 $end
$var wire 1 " s $end
$var wire 2 I w [1:0] $end
$var reg 1 J f $end
$upscope $end
$scope module mux26 $end
$var wire 1 " s $end
$var wire 2 K w [1:0] $end
$var reg 1 L f $end
$upscope $end
$scope module mux27 $end
$var wire 1 " s $end
$var wire 2 M w [1:0] $end
$var reg 1 N f $end
$upscope $end
$scope module mux28 $end
$var wire 1 " s $end
$var wire 2 O w [1:0] $end
$var reg 1 P f $end
$upscope $end
$scope module mux29 $end
$var wire 1 " s $end
$var wire 2 Q w [1:0] $end
$var reg 1 R f $end
$upscope $end
$scope module mux3 $end
$var wire 1 " s $end
$var wire 2 S w [1:0] $end
$var reg 1 T f $end
$upscope $end
$scope module mux30 $end
$var wire 1 " s $end
$var wire 2 U w [1:0] $end
$var reg 1 V f $end
$upscope $end
$scope module mux31 $end
$var wire 1 " s $end
$var wire 2 W w [1:0] $end
$var reg 1 X f $end
$upscope $end
$scope module mux32 $end
$var wire 1 " s $end
$var wire 2 Y w [1:0] $end
$var reg 1 Z f $end
$upscope $end
$scope module mux33 $end
$var wire 1 " s $end
$var wire 2 [ w [1:0] $end
$var reg 1 \ f $end
$upscope $end
$scope module mux34 $end
$var wire 1 " s $end
$var wire 2 ] w [1:0] $end
$var reg 1 ^ f $end
$upscope $end
$scope module mux35 $end
$var wire 1 " s $end
$var wire 2 _ w [1:0] $end
$var reg 1 ` f $end
$upscope $end
$scope module mux36 $end
$var wire 1 " s $end
$var wire 2 a w [1:0] $end
$var reg 1 b f $end
$upscope $end
$scope module mux37 $end
$var wire 1 " s $end
$var wire 2 c w [1:0] $end
$var reg 1 d f $end
$upscope $end
$scope module mux38 $end
$var wire 1 " s $end
$var wire 2 e w [1:0] $end
$var reg 1 f f $end
$upscope $end
$scope module mux39 $end
$var wire 1 " s $end
$var wire 2 g w [1:0] $end
$var reg 1 h f $end
$upscope $end
$scope module mux4 $end
$var wire 1 " s $end
$var wire 2 i w [1:0] $end
$var reg 1 j f $end
$upscope $end
$scope module mux40 $end
$var wire 1 " s $end
$var wire 2 k w [1:0] $end
$var reg 1 l f $end
$upscope $end
$scope module mux41 $end
$var wire 1 " s $end
$var wire 2 m w [1:0] $end
$var reg 1 n f $end
$upscope $end
$scope module mux42 $end
$var wire 1 " s $end
$var wire 2 o w [1:0] $end
$var reg 1 p f $end
$upscope $end
$scope module mux43 $end
$var wire 1 " s $end
$var wire 2 q w [1:0] $end
$var reg 1 r f $end
$upscope $end
$scope module mux44 $end
$var wire 1 " s $end
$var wire 2 s w [1:0] $end
$var reg 1 t f $end
$upscope $end
$scope module mux45 $end
$var wire 1 " s $end
$var wire 2 u w [1:0] $end
$var reg 1 v f $end
$upscope $end
$scope module mux46 $end
$var wire 1 " s $end
$var wire 2 w w [1:0] $end
$var reg 1 x f $end
$upscope $end
$scope module mux47 $end
$var wire 1 " s $end
$var wire 2 y w [1:0] $end
$var reg 1 z f $end
$upscope $end
$scope module mux48 $end
$var wire 1 " s $end
$var wire 2 { w [1:0] $end
$var reg 1 | f $end
$upscope $end
$scope module mux49 $end
$var wire 1 " s $end
$var wire 2 } w [1:0] $end
$var reg 1 ~ f $end
$upscope $end
$scope module mux5 $end
$var wire 1 " s $end
$var wire 2 !" w [1:0] $end
$var reg 1 "" f $end
$upscope $end
$scope module mux50 $end
$var wire 1 " s $end
$var wire 2 #" w [1:0] $end
$var reg 1 $" f $end
$upscope $end
$scope module mux51 $end
$var wire 1 " s $end
$var wire 2 %" w [1:0] $end
$var reg 1 &" f $end
$upscope $end
$scope module mux52 $end
$var wire 1 " s $end
$var wire 2 '" w [1:0] $end
$var reg 1 (" f $end
$upscope $end
$scope module mux53 $end
$var wire 1 " s $end
$var wire 2 )" w [1:0] $end
$var reg 1 *" f $end
$upscope $end
$scope module mux54 $end
$var wire 1 " s $end
$var wire 2 +" w [1:0] $end
$var reg 1 ," f $end
$upscope $end
$scope module mux55 $end
$var wire 1 " s $end
$var wire 2 -" w [1:0] $end
$var reg 1 ." f $end
$upscope $end
$scope module mux56 $end
$var wire 1 " s $end
$var wire 2 /" w [1:0] $end
$var reg 1 0" f $end
$upscope $end
$scope module mux57 $end
$var wire 1 " s $end
$var wire 2 1" w [1:0] $end
$var reg 1 2" f $end
$upscope $end
$scope module mux58 $end
$var wire 1 " s $end
$var wire 2 3" w [1:0] $end
$var reg 1 4" f $end
$upscope $end
$scope module mux59 $end
$var wire 1 " s $end
$var wire 2 5" w [1:0] $end
$var reg 1 6" f $end
$upscope $end
$scope module mux6 $end
$var wire 1 " s $end
$var wire 2 7" w [1:0] $end
$var reg 1 8" f $end
$upscope $end
$scope module mux60 $end
$var wire 1 " s $end
$var wire 2 9" w [1:0] $end
$var reg 1 :" f $end
$upscope $end
$scope module mux61 $end
$var wire 1 " s $end
$var wire 2 ;" w [1:0] $end
$var reg 1 <" f $end
$upscope $end
$scope module mux62 $end
$var wire 1 " s $end
$var wire 2 =" w [1:0] $end
$var reg 1 >" f $end
$upscope $end
$scope module mux63 $end
$var wire 1 " s $end
$var wire 2 ?" w [1:0] $end
$var reg 1 @" f $end
$upscope $end
$scope module mux64 $end
$var wire 1 " s $end
$var wire 2 A" w [1:0] $end
$var reg 1 B" f $end
$upscope $end
$scope module mux7 $end
$var wire 1 " s $end
$var wire 2 C" w [1:0] $end
$var reg 1 D" f $end
$upscope $end
$scope module mux8 $end
$var wire 1 " s $end
$var wire 2 E" w [1:0] $end
$var reg 1 F" f $end
$upscope $end
$scope module mux9 $end
$var wire 1 " s $end
$var wire 2 G" w [1:0] $end
$var reg 1 H" f $end
$upscope $end
$upscope $end
$upscope $end
$enddefinitions $end
#0
$dumpvars
0H"
b0 G"
0F"
b0 E"
0D"
b0 C"
0B"
b0 A"
0@"
b0 ?"
0>"
b0 ="
0<"
b0 ;"
0:"
b0 9"
08"
b0 7"
06"
b0 5"
04"
b0 3"
02"
b0 1"
00"
b0 /"
0."
b0 -"
0,"
b0 +"
0*"
b0 )"
0("
b0 '"
0&"
b0 %"
0$"
b0 #"
0""
b0 !"
0~
b0 }
0|
b0 {
0z
b0 y
0x
b0 w
0v
b0 u
0t
b0 s
0r
b0 q
0p
b0 o
0n
b0 m
0l
b0 k
0j
b0 i
0h
b0 g
0f
b0 e
0d
b0 c
0b
b0 a
0`
b0 _
0^
b0 ]
0\
b0 [
0Z
b0 Y
0X
b0 W
0V
b0 U
0T
b0 S
0R
b0 Q
0P
b0 O
0N
b0 M
0L
b0 K
0J
b0 I
0H
b0 G
0F
b0 E
0D
b0 C
0B
b0 A
0@
b0 ?
0>
b0 =
0<
b0 ;
0:
b0 9
08
b0 7
06
b0 5
04
b0 3
02
b0 1
00
b0 /
0.
b0 -
0,
b0 +
0*
b0 )
0(
b0 '
b0 &
b0 %
b10000000 $
b0 #
0"
b0 !
$end
#10
1"
b1000000 $
#20
b1 !
b1 &
1B"
b1 A"
0"
b1 #
b1 %
b10000000 $
#30
b0 !
b0 &
0B"
1"
b11111111111111111111111111111111 $
#40
b10 A"
0"
b10 #
b10 %
b10000000 $
#50
b1 !
b1 &
1B"
1"
b11111111111111111111111111111111 $
#60
b11 A"
0"
b11 #
b11 %
b10000000 $
#70
1"
b11111111111111111111111111111111 $
#80
1@"
b10 !
b10 &
0B"
b1 ?"
b0 A"
0"
b100 #
b100 %
b10000000 $
#90
b0 !
b0 &
0@"
1"
b11111111111111111111111111111111 $
#100
b10 !
b10 &
1@"
b10 A"
0"
b110 #
b110 %
b10000000 $
#110
0@"
b1 !
b1 &
1B"
1"
b11111111111111111111111111111111 $
#120
b11 !
b11 &
1@"
b1 A"
0"
b101 #
b101 %
b10000000 $
#130
0@"
b0 !
b0 &
0B"
1"
b11111111111111111111111111111111 $
#140
1@"
b11 !
b11 &
1B"
b11 A"
0"
b111 #
b111 %
b10000000 $
#150
b1 !
b1 &
0@"
1"
b11111111111111111111111111111111 $
#160
b11111111111111111111111111111111 $
