register file/register_file.v


module register_file (
    r_19_15, r_24_10, r_11_7_w, write_data, read_data_one, read_data_two, clk, regWr
);
input [4:0] r_19_15, r_24_10, r_11_7_w;
input [63:0] write_data;
input clk;
input regWr;
output [63:0] read_data_one;
output [63:0] read_data_two;

reg [63:0] registers [31:0];

assign #2 read_data_one = registers[r_19_15];
assign #2 read_data_two = registers[r_24_10];

always @(posedge clk) begin
    if(regWr)
        registers[r_11_7_w] <= #3 write_data;
        
end
    
endmodule

register file/register_file_tb.v
 `timescale 1ns/1ns
 `include "register_file.v"
 
 module register_file_tb;

 reg clk;
 reg [63:0] W;
 reg [4:0] R1, R2, RW;
 reg rw;
 wire [63:0] one, two;

register_file UUT(
    .r_19_15(R1),
    .r_24_10(R2),
    .r_11_7_w(RW),
    .clk(clk),
    .write_data(W),
    .read_data_one(one),
    .read_data_two(two),
    .regWr(rw)
);

always #5 clk = ~clk;

initial begin
    $dumpfile("register_file_tb.vcd");
    $dumpvars(0, register_file_tb);
end

initial begin
      clk = 1;
      rw = 0;
      R1  = 5'd0;
      R2  = 5'd0;
      RW  = 5'd0;
      W   = 64'd0;
      
      #80 W   = 64'd2500;
      #2  RW  = 5'd2;
      #2  rw = 1;
      #30 rw = 0;
          W   = 64'd0;
          RW  = 5'd0;
      
      #80 W   = 64'd2555;
      #2  RW  = 5'd19;
      #2  rw = 1;
      #30 rw = 0;
          W   = 64'd0;
          RW  = 5'd0;
      
      #80 W   = 64'd2555;
      #2  RW  = 5'd31;
      #2  rw = 1;
      #30 rw = 0;
          W   = 64'd0;
          RW  = 5'd0;
 
      #80 R1  = 5'd31;
          R2  = 5'd19;
      #10 R1  = 5'd19;
          R2  = 5'd2;
      #30
    $finish;
    end

 endmodule

register file/register_file_tb.vcd
$date
	Fri Dec 10 13:50:51 2021
$end
$version
	Icarus Verilog
$end
$timescale
	1ns
$end
$scope module register_file_tb $end
$var wire 64 ! two [63:0] $end
$var wire 64 " one [63:0] $end
$var reg 5 # R1 [4:0] $end
$var reg 5 $ R2 [4:0] $end
$var reg 5 % RW [4:0] $end
$var reg 64 & W [63:0] $end
$var reg 1 ' clk $end
$var reg 1 ( rw $end
$scope module UUT $end
$var wire 1 ' clk $end
$var wire 5 ) r_11_7_w [4:0] $end
$var wire 5 * r_19_15 [4:0] $end
$var wire 5 + r_24_10 [4:0] $end
$var wire 64 , read_data_one [63:0] $end
$var wire 64 - read_data_two [63:0] $end
$var wire 1 ( regWr $end
$var wire 64 . write_data [63:0] $end
$upscope $end
$upscope $end
$enddefinitions $end
#0
$dumpvars
b0 .
bx -
bx ,
b0 +
b0 *
b0 )
0(
1'
b0 &
b0 %
b0 $
b0 #
bx "
bx !
$end
#5
0'
#10
1'
#15
0'
#20
1'
#25
0'
#30
1'
#35
0'
#40
1'
#45
0'
#50
1'
#55
0'
#60
1'
#65
0'
#70
1'
#75
0'
#80
1'
b100111000100 &
b100111000100 .
#82
b10 %
b10 )
#84
1(
#85
0'
#90
1'
#95
0'
#100
1'
#105
0'
#110
1'
#114
b0 %
b0 )
b0 &
b0 .
0(
#115
0'
#120
1'
#125
0'
#130
1'
#135
0'
#140
1'
#145
0'
#150
1'
#155
0'
#160
1'
#165
0'
#170
1'
#175
0'
#180
1'
#185
0'
#190
1'
#194
b100111111011 &
b100111111011 .
#195
0'
#196
b10011 %
b10011 )
#198
1(
#200
1'
#205
0'
#210
1'
#215
0'
#220
1'
#225
0'
#228
b0 %
b0 )
b0 &
b0 .
0(
#230
1'
#235
0'
#240
1'
#245
0'
#250
1'
#255
0'
#260
1'
#265
0'
#270
1'
#275
0'
#280
1'
#285
0'
#290
1'
#295
0'
#300
1'
#305
0'
#308
b100111111011 &
b100111111011 .
#310
b11111 %
b11111 )
1'
#312
1(
#315
0'
#320
1'
#325
0'
#330
1'
#335
0'
#340
1'
#342
b0 %
b0 )
b0 &
b0 .
0(
#345
0'
#350
1'
#355
0'
#360
1'
#365
0'
#370
1'
#375
0'
#380
1'
#385
0'
#390
1'
#395
0'
#400
1'
#405
0'
#410
1'
#415
0'
#420
1'
#422
b10011 $
b10011 +
b11111 #
b11111 *
#424
b100111111011 !
b100111111011 -
b100111111011 "
b100111111011 ,
#425
0'
#430
1'
#432
b10 $
b10 +
b10011 #
b10011 *
#434
b100111000100 !
b100111000100 -
